jufinance/__init__.py
jufinance/quote.py
jufinance/scrapers/__init__.py
jufinance/scrapers/investing.py
jufinance/scrapers/moneycontrol.py
jufinance/scrapers/screener.py
jufinance/scrapers/data/__init__.py
jufinance/scrapers/data/links.py
jufinance-0.1.0.dist-info/METADATA
jufinance-0.1.0.dist-info/WHEEL
jufinance-0.1.0.dist-info/top_level.txt
jufinance-0.1.0.dist-info/RECORD
