Metadata-Version: 2.1
Name: jufinance
Version: 0.1.0
Summary: Python Package to access Indian Stock market data.
Home-page: https://github.com/prkedia81/jufinance
Author: Prannay Kedia & Sparsh Gupta
Author-email: prannaykedia1@gmail.com, sparshgupta2407@gmail.com
License: MIT
Keywords: python,finance,stock market
Classifier: Intended Audience :: Developers
Classifier: Programming Language :: Python :: 3
Requires-Dist: beautifulsoup4
Requires-Dist: bs4
Requires-Dist: pandas
Requires-Dist: requests
Requires-Dist: selenium
